calculatorkz/__init__.py
calculatorkz/calculatorkz.py
calculatorkz-0.1.0.dist-info/LICENSE
calculatorkz-0.1.0.dist-info/WHEEL
calculatorkz-0.1.0.dist-info/METADATA
calculatorkz-0.1.0.dist-info/RECORD
