Metadata-Version: 2.1
Name: calculatorkz
Version: 0.1.0
Summary: Run the code
Author-email: Kristina Zekiene <kristina.zekiene@gmail.com>
Classifier: License :: OSI Approved :: MIT License
Project-URL: Home, https://github.com/kristinazekiene/calculatorkz
